visionml_utils/__init__.py
visionml_utils/yolov8/__init__.py
visionml_utils/yolov8/scripts/ModelTrainer.py
visionml_utils/yolov8/scripts/ModelTuner.py
visionml_utils/yolov8/scripts/ModelValidator.py
visionml_utils/yolov8/scripts/VideoProcessor.py
visionml_utils/yolov8/scripts/__init__.py
visionml_utils-1.0.0.dist-info/LICENSE
visionml_utils-1.0.0.dist-info/METADATA
visionml_utils-1.0.0.dist-info/WHEEL
visionml_utils-1.0.0.dist-info/top_level.txt
visionml_utils-1.0.0.dist-info/RECORD
