Metadata-Version: 2.1
Name: visionml-utils
Version: 1.0.0
Summary: Util scripts and files for computer vision deep learning models.
Author: Alvin Zhu
License: MIT
Project-URL: GitHub, https://github.com/alvister88/Vision-Utils
Classifier: Development Status :: 4 - Beta
Classifier: Intended Audience :: Developers
Classifier: Intended Audience :: Education
Classifier: Intended Audience :: Science/Research
Classifier: Programming Language :: Python :: 3
License-File: LICENSE
Requires-Dist: numpy
Requires-Dist: ultralytics
Requires-Dist: wandb
Requires-Dist: pathlib
